{
  "level": "B1",
  "topic_key": "frasi_causali",
  "topic_name": "Frasi causali",
  "exercises": [
    {
      "id": 1,
      "question": "Completa la frase: ___",
      "options": [
        "perché",
        "poiché",
        "siccome"
      ],
      "answer": "poiché",
      "explanation": "Risposta corretta: poiché"
    },
    {
      "id": 2,
      "question": "Completa la frase: ___",
      "options": [
        "perché",
        "siccome",
        "poiché"
      ],
      "answer": "poiché",
      "explanation": "Risposta corretta: poiché"
    },
    {
      "id": 3,
      "question": "Completa la frase: ___",
      "options": [
        "poiché",
        "siccome",
        "perché"
      ],
      "answer": "siccome",
      "explanation": "Risposta corretta: siccome"
    },
    {
      "id": 4,
      "question": "Completa la frase: ___",
      "options": [
        "perché",
        "siccome",
        "poiché"
      ],
      "answer": "siccome",
      "explanation": "Risposta corretta: siccome"
    },
    {
      "id": 5,
      "question": "Completa la frase: ___",
      "options": [
        "siccome",
        "perché",
        "poiché"
      ],
      "answer": "siccome",
      "explanation": "Risposta corretta: siccome"
    },
    {
      "id": 6,
      "question": "Completa la frase: ___",
      "options": [
        "perché",
        "poiché",
        "siccome"
      ],
      "answer": "perché",
      "explanation": "Risposta corretta: perché"
    },
    {
      "id": 7,
      "question": "Completa la frase: ___",
      "options": [
        "perché",
        "siccome",
        "poiché"
      ],
      "answer": "perché",
      "explanation": "Risposta corretta: perché"
    },
    {
      "id": 8,
      "question": "Completa la frase: ___",
      "options": [
        "poiché",
        "siccome",
        "perché"
      ],
      "answer": "poiché",
      "explanation": "Risposta corretta: poiché"
    },
    {
      "id": 9,
      "question": "Completa la frase: ___",
      "options": [
        "poiché",
        "perché",
        "siccome"
      ],
      "answer": "poiché",
      "explanation": "Risposta corretta: poiché"
    },
    {
      "id": 10,
      "question": "Completa la frase: ___",
      "options": [
        "siccome",
        "perché",
        "poiché"
      ],
      "answer": "siccome",
      "explanation": "Risposta corretta: siccome"
    },
    {
      "id": 11,
      "question": "Completa la frase: ___",
      "options": [
        "siccome",
        "perché",
        "poiché"
      ],
      "answer": "siccome",
      "explanation": "Risposta corretta: siccome"
    },
    {
      "id": 12,
      "question": "Completa la frase: ___",
      "options": [
        "perché",
        "siccome",
        "poiché"
      ],
      "answer": "siccome",
      "explanation": "Risposta corretta: siccome"
    },
    {
      "id": 13,
      "question": "Completa la frase: ___",
      "options": [
        "perché",
        "poiché",
        "siccome"
      ],
      "answer": "poiché",
      "explanation": "Risposta corretta: poiché"
    },
    {
      "id": 14,
      "question": "Completa la frase: ___",
      "options": [
        "poiché",
        "siccome",
        "perché"
      ],
      "answer": "siccome",
      "explanation": "Risposta corretta: siccome"
    },
    {
      "id": 15,
      "question": "Completa la frase: ___",
      "options": [
        "poiché",
        "perché",
        "siccome"
      ],
      "answer": "perché",
      "explanation": "Risposta corretta: perché"
    },
    {
      "id": 16,
      "question": "Completa la frase: ___",
      "options": [
        "poiché",
        "perché",
        "siccome"
      ],
      "answer": "siccome",
      "explanation": "Risposta corretta: siccome"
    },
    {
      "id": 17,
      "question": "Completa la frase: ___",
      "options": [
        "poiché",
        "perché",
        "siccome"
      ],
      "answer": "siccome",
      "explanation": "Risposta corretta: siccome"
    },
    {
      "id": 18,
      "question": "Completa la frase: ___",
      "options": [
        "siccome",
        "perché",
        "poiché"
      ],
      "answer": "perché",
      "explanation": "Risposta corretta: perché"
    },
    {
      "id": 19,
      "question": "Completa la frase: ___",
      "options": [
        "poiché",
        "perché",
        "siccome"
      ],
      "answer": "poiché",
      "explanation": "Risposta corretta: poiché"
    },
    {
      "id": 20,
      "question": "Completa la frase: ___",
      "options": [
        "perché",
        "siccome",
        "poiché"
      ],
      "answer": "poiché",
      "explanation": "Risposta corretta: poiché"
    },
    {
      "id": 21,
      "question": "Completa la frase: ___",
      "options": [
        "siccome",
        "perché",
        "poiché"
      ],
      "answer": "perché",
      "explanation": "Risposta corretta: perché"
    },
    {
      "id": 22,
      "question": "Completa la frase: ___",
      "options": [
        "siccome",
        "poiché",
        "perché"
      ],
      "answer": "perché",
      "explanation": "Risposta corretta: perché"
    },
    {
      "id": 23,
      "question": "Completa la frase: ___",
      "options": [
        "siccome",
        "poiché",
        "perché"
      ],
      "answer": "siccome",
      "explanation": "Risposta corretta: siccome"
    },
    {
      "id": 24,
      "question": "Completa la frase: ___",
      "options": [
        "siccome",
        "poiché",
        "perché"
      ],
      "answer": "poiché",
      "explanation": "Risposta corretta: poiché"
    },
    {
      "id": 25,
      "question": "Completa la frase: ___",
      "options": [
        "perché",
        "poiché",
        "siccome"
      ],
      "answer": "siccome",
      "explanation": "Risposta corretta: siccome"
    },
    {
      "id": 26,
      "question": "Completa la frase: ___",
      "options": [
        "siccome",
        "perché",
        "poiché"
      ],
      "answer": "siccome",
      "explanation": "Risposta corretta: siccome"
    },
    {
      "id": 27,
      "question": "Completa la frase: ___",
      "options": [
        "poiché",
        "perché",
        "siccome"
      ],
      "answer": "poiché",
      "explanation": "Risposta corretta: poiché"
    },
    {
      "id": 28,
      "question": "Completa la frase: ___",
      "options": [
        "perché",
        "siccome",
        "poiché"
      ],
      "answer": "poiché",
      "explanation": "Risposta corretta: poiché"
    },
    {
      "id": 29,
      "question": "Completa la frase: ___",
      "options": [
        "poiché",
        "siccome",
        "perché"
      ],
      "answer": "siccome",
      "explanation": "Risposta corretta: siccome"
    },
    {
      "id": 30,
      "question": "Completa la frase: ___",
      "options": [
        "siccome",
        "perché",
        "poiché"
      ],
      "answer": "perché",
      "explanation": "Risposta corretta: perché"
    },
    {
      "id": 31,
      "question": "Completa la frase: ___",
      "options": [
        "siccome",
        "perché",
        "poiché"
      ],
      "answer": "poiché",
      "explanation": "Risposta corretta: poiché"
    },
    {
      "id": 32,
      "question": "Completa la frase: ___",
      "options": [
        "poiché",
        "siccome",
        "perché"
      ],
      "answer": "perché",
      "explanation": "Risposta corretta: perché"
    },
    {
      "id": 33,
      "question": "Completa la frase: ___",
      "options": [
        "siccome",
        "perché",
        "poiché"
      ],
      "answer": "poiché",
      "explanation": "Risposta corretta: poiché"
    },
    {
      "id": 34,
      "question": "Completa la frase: ___",
      "options": [
        "poiché",
        "siccome",
        "perché"
      ],
      "answer": "perché",
      "explanation": "Risposta corretta: perché"
    },
    {
      "id": 35,
      "question": "Completa la frase: ___",
      "options": [
        "perché",
        "siccome",
        "poiché"
      ],
      "answer": "poiché",
      "explanation": "Risposta corretta: poiché"
    },
    {
      "id": 36,
      "question": "Completa la frase: ___",
      "options": [
        "siccome",
        "perché",
        "poiché"
      ],
      "answer": "siccome",
      "explanation": "Risposta corretta: siccome"
    },
    {
      "id": 37,
      "question": "Completa la frase: ___",
      "options": [
        "siccome",
        "poiché",
        "perché"
      ],
      "answer": "poiché",
      "explanation": "Risposta corretta: poiché"
    },
    {
      "id": 38,
      "question": "Completa la frase: ___",
      "options": [
        "perché",
        "siccome",
        "poiché"
      ],
      "answer": "perché",
      "explanation": "Risposta corretta: perché"
    },
    {
      "id": 39,
      "question": "Completa la frase: ___",
      "options": [
        "poiché",
        "siccome",
        "perché"
      ],
      "answer": "poiché",
      "explanation": "Risposta corretta: poiché"
    },
    {
      "id": 40,
      "question": "Completa la frase: ___",
      "options": [
        "siccome",
        "perché",
        "poiché"
      ],
      "answer": "poiché",
      "explanation": "Risposta corretta: poiché"
    },
    {
      "id": 41,
      "question": "Completa la frase: ___",
      "options": [
        "siccome",
        "poiché",
        "perché"
      ],
      "answer": "poiché",
      "explanation": "Risposta corretta: poiché"
    },
    {
      "id": 42,
      "question": "Completa la frase: ___",
      "options": [
        "poiché",
        "siccome",
        "perché"
      ],
      "answer": "poiché",
      "explanation": "Risposta corretta: poiché"
    },
    {
      "id": 43,
      "question": "Completa la frase: ___",
      "options": [
        "perché",
        "poiché",
        "siccome"
      ],
      "answer": "poiché",
      "explanation": "Risposta corretta: poiché"
    },
    {
      "id": 44,
      "question": "Completa la frase: ___",
      "options": [
        "perché",
        "siccome",
        "poiché"
      ],
      "answer": "poiché",
      "explanation": "Risposta corretta: poiché"
    },
    {
      "id": 45,
      "question": "Completa la frase: ___",
      "options": [
        "poiché",
        "siccome",
        "perché"
      ],
      "answer": "siccome",
      "explanation": "Risposta corretta: siccome"
    },
    {
      "id": 46,
      "question": "Completa la frase: ___",
      "options": [
        "poiché",
        "perché",
        "siccome"
      ],
      "answer": "perché",
      "explanation": "Risposta corretta: perché"
    },
    {
      "id": 47,
      "question": "Completa la frase: ___",
      "options": [
        "poiché",
        "perché",
        "siccome"
      ],
      "answer": "poiché",
      "explanation": "Risposta corretta: poiché"
    },
    {
      "id": 48,
      "question": "Completa la frase: ___",
      "options": [
        "siccome",
        "perché",
        "poiché"
      ],
      "answer": "perché",
      "explanation": "Risposta corretta: perché"
    },
    {
      "id": 49,
      "question": "Completa la frase: ___",
      "options": [
        "siccome",
        "perché",
        "poiché"
      ],
      "answer": "perché",
      "explanation": "Risposta corretta: perché"
    },
    {
      "id": 50,
      "question": "Completa la frase: ___",
      "options": [
        "poiché",
        "perché",
        "siccome"
      ],
      "answer": "siccome",
      "explanation": "Risposta corretta: siccome"
    },
    {
      "id": 51,
      "question": "Completa la frase: ___",
      "options": [
        "poiché",
        "perché",
        "siccome"
      ],
      "answer": "poiché",
      "explanation": "Risposta corretta: poiché"
    },
    {
      "id": 52,
      "question": "Completa la frase: ___",
      "options": [
        "perché",
        "poiché",
        "siccome"
      ],
      "answer": "poiché",
      "explanation": "Risposta corretta: poiché"
    },
    {
      "id": 53,
      "question": "Completa la frase: ___",
      "options": [
        "perché",
        "poiché",
        "siccome"
      ],
      "answer": "siccome",
      "explanation": "Risposta corretta: siccome"
    },
    {
      "id": 54,
      "question": "Completa la frase: ___",
      "options": [
        "perché",
        "poiché",
        "siccome"
      ],
      "answer": "poiché",
      "explanation": "Risposta corretta: poiché"
    },
    {
      "id": 55,
      "question": "Completa la frase: ___",
      "options": [
        "siccome",
        "poiché",
        "perché"
      ],
      "answer": "siccome",
      "explanation": "Risposta corretta: siccome"
    },
    {
      "id": 56,
      "question": "Completa la frase: ___",
      "options": [
        "siccome",
        "poiché",
        "perché"
      ],
      "answer": "poiché",
      "explanation": "Risposta corretta: poiché"
    },
    {
      "id": 57,
      "question": "Completa la frase: ___",
      "options": [
        "poiché",
        "siccome",
        "perché"
      ],
      "answer": "siccome",
      "explanation": "Risposta corretta: siccome"
    },
    {
      "id": 58,
      "question": "Completa la frase: ___",
      "options": [
        "perché",
        "siccome",
        "poiché"
      ],
      "answer": "poiché",
      "explanation": "Risposta corretta: poiché"
    },
    {
      "id": 59,
      "question": "Completa la frase: ___",
      "options": [
        "poiché",
        "siccome",
        "perché"
      ],
      "answer": "poiché",
      "explanation": "Risposta corretta: poiché"
    },
    {
      "id": 60,
      "question": "Completa la frase: ___",
      "options": [
        "perché",
        "siccome",
        "poiché"
      ],
      "answer": "perché",
      "explanation": "Risposta corretta: perché"
    },
    {
      "id": 61,
      "question": "Completa la frase: ___",
      "options": [
        "siccome",
        "perché",
        "poiché"
      ],
      "answer": "siccome",
      "explanation": "Risposta corretta: siccome"
    },
    {
      "id": 62,
      "question": "Completa la frase: ___",
      "options": [
        "perché",
        "siccome",
        "poiché"
      ],
      "answer": "perché",
      "explanation": "Risposta corretta: perché"
    },
    {
      "id": 63,
      "question": "Completa la frase: ___",
      "options": [
        "perché",
        "poiché",
        "siccome"
      ],
      "answer": "siccome",
      "explanation": "Risposta corretta: siccome"
    },
    {
      "id": 64,
      "question": "Completa la frase: ___",
      "options": [
        "siccome",
        "perché",
        "poiché"
      ],
      "answer": "perché",
      "explanation": "Risposta corretta: perché"
    },
    {
      "id": 65,
      "question": "Completa la frase: ___",
      "options": [
        "perché",
        "siccome",
        "poiché"
      ],
      "answer": "siccome",
      "explanation": "Risposta corretta: siccome"
    },
    {
      "id": 66,
      "question": "Completa la frase: ___",
      "options": [
        "poiché",
        "siccome",
        "perché"
      ],
      "answer": "siccome",
      "explanation": "Risposta corretta: siccome"
    },
    {
      "id": 67,
      "question": "Completa la frase: ___",
      "options": [
        "poiché",
        "perché",
        "siccome"
      ],
      "answer": "siccome",
      "explanation": "Risposta corretta: siccome"
    },
    {
      "id": 68,
      "question": "Completa la frase: ___",
      "options": [
        "poiché",
        "siccome",
        "perché"
      ],
      "answer": "siccome",
      "explanation": "Risposta corretta: siccome"
    },
    {
      "id": 69,
      "question": "Completa la frase: ___",
      "options": [
        "siccome",
        "perché",
        "poiché"
      ],
      "answer": "perché",
      "explanation": "Risposta corretta: perché"
    },
    {
      "id": 70,
      "question": "Completa la frase: ___",
      "options": [
        "siccome",
        "poiché",
        "perché"
      ],
      "answer": "siccome",
      "explanation": "Risposta corretta: siccome"
    },
    {
      "id": 71,
      "question": "Completa la frase: ___",
      "options": [
        "siccome",
        "perché",
        "poiché"
      ],
      "answer": "siccome",
      "explanation": "Risposta corretta: siccome"
    },
    {
      "id": 72,
      "question": "Completa la frase: ___",
      "options": [
        "siccome",
        "poiché",
        "perché"
      ],
      "answer": "poiché",
      "explanation": "Risposta corretta: poiché"
    },
    {
      "id": 73,
      "question": "Completa la frase: ___",
      "options": [
        "perché",
        "poiché",
        "siccome"
      ],
      "answer": "siccome",
      "explanation": "Risposta corretta: siccome"
    },
    {
      "id": 74,
      "question": "Completa la frase: ___",
      "options": [
        "perché",
        "siccome",
        "poiché"
      ],
      "answer": "poiché",
      "explanation": "Risposta corretta: poiché"
    },
    {
      "id": 75,
      "question": "Completa la frase: ___",
      "options": [
        "siccome",
        "perché",
        "poiché"
      ],
      "answer": "siccome",
      "explanation": "Risposta corretta: siccome"
    },
    {
      "id": 76,
      "question": "Completa la frase: ___",
      "options": [
        "perché",
        "poiché",
        "siccome"
      ],
      "answer": "perché",
      "explanation": "Risposta corretta: perché"
    },
    {
      "id": 77,
      "question": "Completa la frase: ___",
      "options": [
        "perché",
        "siccome",
        "poiché"
      ],
      "answer": "poiché",
      "explanation": "Risposta corretta: poiché"
    },
    {
      "id": 78,
      "question": "Completa la frase: ___",
      "options": [
        "perché",
        "siccome",
        "poiché"
      ],
      "answer": "poiché",
      "explanation": "Risposta corretta: poiché"
    },
    {
      "id": 79,
      "question": "Completa la frase: ___",
      "options": [
        "poiché",
        "perché",
        "siccome"
      ],
      "answer": "poiché",
      "explanation": "Risposta corretta: poiché"
    },
    {
      "id": 80,
      "question": "Completa la frase: ___",
      "options": [
        "siccome",
        "perché",
        "poiché"
      ],
      "answer": "poiché",
      "explanation": "Risposta corretta: poiché"
    },
    {
      "id": 81,
      "question": "Completa la frase: ___",
      "options": [
        "siccome",
        "perché",
        "poiché"
      ],
      "answer": "siccome",
      "explanation": "Risposta corretta: siccome"
    },
    {
      "id": 82,
      "question": "Completa la frase: ___",
      "options": [
        "siccome",
        "poiché",
        "perché"
      ],
      "answer": "siccome",
      "explanation": "Risposta corretta: siccome"
    },
    {
      "id": 83,
      "question": "Completa la frase: ___",
      "options": [
        "poiché",
        "siccome",
        "perché"
      ],
      "answer": "siccome",
      "explanation": "Risposta corretta: siccome"
    },
    {
      "id": 84,
      "question": "Completa la frase: ___",
      "options": [
        "poiché",
        "perché",
        "siccome"
      ],
      "answer": "poiché",
      "explanation": "Risposta corretta: poiché"
    },
    {
      "id": 85,
      "question": "Completa la frase: ___",
      "options": [
        "perché",
        "poiché",
        "siccome"
      ],
      "answer": "siccome",
      "explanation": "Risposta corretta: siccome"
    },
    {
      "id": 86,
      "question": "Completa la frase: ___",
      "options": [
        "poiché",
        "siccome",
        "perché"
      ],
      "answer": "poiché",
      "explanation": "Risposta corretta: poiché"
    },
    {
      "id": 87,
      "question": "Completa la frase: ___",
      "options": [
        "siccome",
        "poiché",
        "perché"
      ],
      "answer": "poiché",
      "explanation": "Risposta corretta: poiché"
    },
    {
      "id": 88,
      "question": "Completa la frase: ___",
      "options": [
        "poiché",
        "perché",
        "siccome"
      ],
      "answer": "poiché",
      "explanation": "Risposta corretta: poiché"
    },
    {
      "id": 89,
      "question": "Completa la frase: ___",
      "options": [
        "perché",
        "siccome",
        "poiché"
      ],
      "answer": "poiché",
      "explanation": "Risposta corretta: poiché"
    },
    {
      "id": 90,
      "question": "Completa la frase: ___",
      "options": [
        "perché",
        "siccome",
        "poiché"
      ],
      "answer": "poiché",
      "explanation": "Risposta corretta: poiché"
    },
    {
      "id": 91,
      "question": "Completa la frase: ___",
      "options": [
        "poiché",
        "siccome",
        "perché"
      ],
      "answer": "poiché",
      "explanation": "Risposta corretta: poiché"
    },
    {
      "id": 92,
      "question": "Completa la frase: ___",
      "options": [
        "perché",
        "siccome",
        "poiché"
      ],
      "answer": "poiché",
      "explanation": "Risposta corretta: poiché"
    },
    {
      "id": 93,
      "question": "Completa la frase: ___",
      "options": [
        "poiché",
        "perché",
        "siccome"
      ],
      "answer": "poiché",
      "explanation": "Risposta corretta: poiché"
    },
    {
      "id": 94,
      "question": "Completa la frase: ___",
      "options": [
        "perché",
        "poiché",
        "siccome"
      ],
      "answer": "perché",
      "explanation": "Risposta corretta: perché"
    },
    {
      "id": 95,
      "question": "Completa la frase: ___",
      "options": [
        "siccome",
        "perché",
        "poiché"
      ],
      "answer": "poiché",
      "explanation": "Risposta corretta: poiché"
    },
    {
      "id": 96,
      "question": "Completa la frase: ___",
      "options": [
        "perché",
        "siccome",
        "poiché"
      ],
      "answer": "poiché",
      "explanation": "Risposta corretta: poiché"
    },
    {
      "id": 97,
      "question": "Completa la frase: ___",
      "options": [
        "siccome",
        "poiché",
        "perché"
      ],
      "answer": "perché",
      "explanation": "Risposta corretta: perché"
    },
    {
      "id": 98,
      "question": "Completa la frase: ___",
      "options": [
        "poiché",
        "perché",
        "siccome"
      ],
      "answer": "perché",
      "explanation": "Risposta corretta: perché"
    },
    {
      "id": 99,
      "question": "Completa la frase: ___",
      "options": [
        "siccome",
        "poiché",
        "perché"
      ],
      "answer": "poiché",
      "explanation": "Risposta corretta: poiché"
    },
    {
      "id": 100,
      "question": "Completa la frase: ___",
      "options": [
        "siccome",
        "perché",
        "poiché"
      ],
      "answer": "poiché",
      "explanation": "Risposta corretta: poiché"
    }
  ]
}